edgedb_orm/__init__.py
edgedb_orm/base_patch.py
edgedb_orm/batch.py
edgedb_orm/cache.py
edgedb_orm/constants.py
edgedb_orm/creating_strings.py
edgedb_orm/enums.py
edgedb_orm/execute.py
edgedb_orm/execute_regex.py
edgedb_orm/generator.py
edgedb_orm/introspection.py
edgedb_orm/nested_resolvers.py
edgedb_orm/node.py
edgedb_orm/resolver.py
edgedb_orm/resolver_helpers.py
edgedb_orm/span.py
edgedb_orm/unset.py
edgedb_orm/validators.py
edgedb_orm-1.0.23.dist-info/METADATA
edgedb_orm-1.0.23.dist-info/WHEEL
edgedb_orm-1.0.23.dist-info/RECORD
